{"chunk_definitions":[{"chunk_id":"csetup_chunk","chunk_label":"setup","document_id":"D2C21200","expansion_state":0,"options":{"engine":"r","include":false,"label":"setup"},"row":9,"row_count":1,"visible":true},{"chunk_id":"ce2z9s168jrh5","chunk_label":"biblioteki","document_id":"D2C21200","expansion_state":0,"options":{"engine":"r","label":"biblioteki","message":false,"warning":false},"row":104,"row_count":1,"visible":true},{"chunk_id":"csar5o1beayr2","chunk_label":"dane1","document_id":"D2C21200","expansion_state":0,"options":{"engine":"r","label":"dane1 "},"row":130,"row_count":1,"visible":true},{"chunk_id":"ccyjd6fxnfvcu","chunk_label":"wykresdane1","document_id":"D2C21200","expansion_state":0,"options":{"echo":false,"engine":"r","label":"wykresdane1","message":false,"warning":false},"row":145,"row_count":1,"visible":true},{"chunk_id":"cv6u6wytycg7i","chunk_label":"dane2","document_id":"D2C21200","expansion_state":0,"options":{"echo":false,"engine":"r","label":"dane2","warning":false},"row":162,"row_count":1,"visible":true},{"chunk_id":"cngs871hkoquf","chunk_label":"wykresdane2","document_id":"D2C21200","expansion_state":0,"options":{"echo":false,"engine":"r","label":"wykresdane2","message":false},"row":177,"row_count":1,"visible":true},{"chunk_id":"ca2r76ie8hmo1","chunk_label":"dane3","document_id":"D2C21200","expansion_state":0,"options":{"echo":false,"engine":"r","label":"dane3"},"row":196,"row_count":1,"visible":true},{"chunk_id":"cxjv0fr9txnfa","chunk_label":"wykresdane3","document_id":"D2C21200","expansion_state":0,"options":{"echo":false,"engine":"r","label":"wykresdane3","message":false},"row":211,"row_count":1,"visible":true},{"chunk_id":"cd7o0s49xp5cz","chunk_label":"dane4","document_id":"D2C21200","expansion_state":0,"options":{"echo":false,"engine":"r","label":"dane4"},"row":228,"row_count":1,"visible":true},{"chunk_id":"cj44mys9c64oa","chunk_label":"wykresdane4","document_id":"D2C21200","expansion_state":0,"options":{"echo":false,"engine":"r","label":"wykresdane4","message":false},"row":243,"row_count":1,"visible":true},{"chunk_id":"cqa43yq2tufxa","chunk_label":"korelacje","document_id":"D2C21200","expansion_state":0,"options":{"engine":"r","label":"korelacje "},"row":255,"row_count":1,"visible":true},{"chunk_id":"cpvx0ib7q4dki","chunk_label":"losowanie","document_id":"D2C21200","expansion_state":0,"options":{"engine":"r","label":"losowanie"},"row":272,"row_count":1,"visible":true}],"chunk_rendered_width":690,"default_chunk_options":{"echo":true},"doc_write_time":1647169277,"working_dir":null}